telegrambotclient/__init__.py
telegrambotclient/api.py
telegrambotclient/base.py
telegrambotclient/bot.py
telegrambotclient/handler.py
telegrambotclient/router.py
telegrambotclient/storage.py
telegrambotclient/ui.py
telegrambotclient/utils.py
py_telegram_bot_client-6.1.dist-info/METADATA
py_telegram_bot_client-6.1.dist-info/WHEEL
py_telegram_bot_client-6.1.dist-info/top_level.txt
py_telegram_bot_client-6.1.dist-info/RECORD
