Metadata-Version: 2.1
Name: py-telegram-bot-client
Version: 6.1
Summary: A Telegram Bot API Python Client
Home-page: https://github.com/ds828/py-telegram-bot-client
Author: ds828
Author-email: songdi19@gmail.com
License: UNKNOWN
Platform: UNKNOWN
Requires-Python: >=3.5
Requires-Dist: ujson
Requires-Dist: urllib3
